nostr_sdk/__init__.py
nostr_sdk/nostr_sdk.py
nostr_sdk/nostr_sdk_ffi.dll
nostr_sdk-0.44.0.dist-info/licenses/LICENSE
nostr_sdk-0.44.0.dist-info/METADATA
nostr_sdk-0.44.0.dist-info/WHEEL
nostr_sdk-0.44.0.dist-info/top_level.txt
nostr_sdk-0.44.0.dist-info/RECORD
