Metadata-Version: 2.4
Name: nostr-sdk
Version: 0.44.0
Summary: Nostr protocol implementation, Relay, RelayPool, high-level client library, NWC client and more.
Author-email: Yuki Kishimoto <yukikishimoto@protonmail.com>
License-Expression: MIT
Project-URL: Homepage, https://rust-nostr.org
Project-URL: documentation, https://rust-nostr.org
Project-URL: repository, https://github.com/rust-nostr/nostr-sdk-ffi
Project-URL: changelog, https://github.com/rust-nostr/nostr-sdk-ffi/blob/master/CHANGELOG.md
Requires-Python: >=3.9
License-File: LICENSE
Dynamic: license-file
